<?xml version="1.0" encoding="UTF-8"?>
<mods xmlns="http://www.loc.gov/mods/v3"
      xmlns:xlink="http://www.w3.org/1999/xlink"
      xmlns:xs="http://www.w3.org/2001/XMLSchema"
      xmlns:xsi="http://www.w3.org/2001/XMLSchema-instance"
      xsi:schemaLocation="http://www.loc.gov/mods/v3 http://www.loc.gov/standards/mods/v3/mods-3-5.xsd"
      version="3.5">
   <identifier type="local">0012_000128_000292_0001</identifier>
   <name>
      <namePart>unknown</namePart>
      <role>
         <roleTerm type="text"
                   authority="marcrelator"
                   valueURI="http://id.loc.gov/vocabulary/relators/cre">Creator</roleTerm>
      </role>
   </name>
   <titleInfo>
      <title>John L. Godsey in the Courthouse</title>
   </titleInfo>
   <typeOfResource>still image</typeOfResource>
   <originInfo>
      <dateCreated>1925</dateCreated>
      <dateCreated encoding="edtf" keyDate="yes">1925</dateCreated>
   </originInfo>
   <physicalDescription>
      <form authority="aat" valueURI="http://vocab.getty.edu/aat/300046300">photographs</form>
   </physicalDescription>
   <abstract>Scopes Trial Photographs, circa 1925, A-77 (A-78), A-77 (8A), John L. Godsey, original defense lawyer for Scopes, A-78 (7A), The Courthouse, (same as L)</abstract>
   <language>
      <languageTerm type="code" authority="iso639-2b">zxx</languageTerm>
   </language>
   <location>
      <physicalLocation>University of Tennessee, Knoxville. Special Collections</physicalLocation>
      <holdingSimple>
         <copyInformation>
            <shelfLocator>Box 1, Folder 2</shelfLocator>
         </copyInformation>
      </holdingSimple>
   </location>
   <subject>
      <name>
         <namePart>Scopes Trial</namePart>
      </name>
   </subject>
   <subject>
      <name authority="naf"
            valueURI="http://id.loc.gov/authorities/names/n79041823">
         <namePart>Scopes, John Thomas</namePart>
      </name>
   </subject>
   <subject>
      <name authority="naf"
            valueURI="http://id.loc.gov/authorities/names/n80044871">
         <namePart>Bryan, William Jennings, 1860-1925</namePart>
      </name>
   </subject>
   <subject>
      <name>
         <namePart>Robinson, Wallace Clarke, 1920-1995</namePart>
      </name>
   </subject>
   <subject>
      <name>
         <namePart>Robinson, Frank Earle, 1881-1957</namePart>
      </name>
   </subject>
   <subject>
      <name>
         <namePart>Robinson, Frank Earle, 1881-1957</namePart>
      </name>
   </subject>
   <relatedItem type="host" displayLabel="Project">
      <titleInfo>
         <title>Of Monkeys and Men: Public and Private Views from the Scopes Trial</title>
      </titleInfo>
   </relatedItem>
   <relatedItem type="host" displayLabel="Collection">
      <titleInfo>
         <title>W.C. Robinson Collection of Scopes Trial Photographs, circa 1925, circa 1976</title>
      </titleInfo>
      <identifier type="local">MS.1091</identifier>
   </relatedItem>
   <accessCondition type="use and reproduction">The copyright interests in this item remain with the creator. For more information, contact Special Collections at special@utk.edu.</accessCondition>
   <recordInfo>
      <recordIdentifier>record_spc_4464</recordIdentifier>
      <recordContentSource>University of Tennessee, Knoxville. Libraries</recordContentSource>
      <languageOfCataloging>
         <languageTerm type="code" authority="iso639-2b">eng</languageTerm>
      </languageOfCataloging>
      <recordOrigin>Created and edited in general conformance to MODS Guidelines (Version 3.5).</recordOrigin>
   </recordInfo>
</mods>
